vlttools/BenchConfig.py
vlttools/__init__.py
Vlttools-0.1.1.dist-info/LICENSE
Vlttools-0.1.1.dist-info/METADATA
Vlttools-0.1.1.dist-info/WHEEL
Vlttools-0.1.1.dist-info/top_level.txt
Vlttools-0.1.1.dist-info/RECORD
