Metadata-Version: 2.1
Name: Vlttools
Version: 0.1.1
Summary: Useful tools for Vlt drives
Author-email: tangfei <fei.tang@danfoss.com>
Classifier: Programming Language :: Python :: 3
Classifier: License :: OSI Approved :: MIT License
Classifier: Operating System :: OS Independent
Requires-Python: >=3.7
License-File: LICENSE
Requires-Dist: vlt-comm (>=0.1.0)
